arvados_cluster_activity/__init__.py
arvados_cluster_activity/_version.py
arvados_cluster_activity/dygraphs.js
arvados_cluster_activity/main.py
arvados_cluster_activity/prometheus.py
arvados_cluster_activity/report.py
arvados_cluster_activity/reportchart.py
arvados_cluster_activity/sortable.js
arvados_cluster_activity/synchronizer.js
arvados_cluster_activity-3.2.0.data/data/share/doc/arvados-cluster-activity/README.rst
arvados_cluster_activity-3.2.0.data/data/share/doc/arvados-cluster-activity/agpl-3.0.txt
arvados_cluster_activity-3.2.0.data/data/share/doc/arvados-cluster-activity/cluster-activity.cwl
arvados_cluster_activity-3.2.0.dist-info/licenses/agpl-3.0.txt
arvados_cluster_activity-3.2.0.dist-info/METADATA
arvados_cluster_activity-3.2.0.dist-info/WHEEL
arvados_cluster_activity-3.2.0.dist-info/entry_points.txt
arvados_cluster_activity-3.2.0.dist-info/top_level.txt
arvados_cluster_activity-3.2.0.dist-info/RECORD
