Metadata-Version: 2.4
Name: arvados-cluster-activity
Version: 3.2.0
Summary: Summarize Arvados cluster activity from audit logs and Prometheus metrics
Author-email: Arvados <info@arvados.org>
License-Expression: AGPL-3.0-only
Project-URL: Homepage, https://arvados.org
Project-URL: Documentation, https://doc.arvados.org
Project-URL: Repository, https://git.arvados.org/arvados.git
Project-URL: Issues, https://dev.arvados.org/projects/arvados/issues
Project-URL: Changelog, https://arvados.org/releases/
Classifier: Development Status :: 5 - Production/Stable
Classifier: Environment :: Console
Classifier: Intended Audience :: Science/Research
Classifier: Operating System :: POSIX
Classifier: Programming Language :: Python :: 3
Classifier: Programming Language :: Python :: 3.10
Classifier: Programming Language :: Python :: 3.11
Classifier: Programming Language :: Python :: 3.12
Classifier: Programming Language :: Python :: 3.13
Classifier: Topic :: Scientific/Engineering :: Bio-Informatics
Requires-Python: ~=3.10
License-File: agpl-3.0.txt
Requires-Dist: arvados-python-client==3.2.0
Provides-Extra: prometheus
Requires-Dist: prometheus-api-client; extra == "prometheus"
Dynamic: license-file
Dynamic: requires-dist
